examples/AgentTemplate.xircuits
examples/ArgumentParameters.xircuits
examples/CompulsoryPorts.xircuits
examples/ControlflowExample.xircuits
examples/DynamicPorts.xircuits
examples/HelloXircuits.xircuits
examples/ParallelProcesses.xircuits
examples/ServiceTemplate.xircuits
examples/SettingVariables.xircuits
examples/XircuitsContext.xircuits
examples/__init__.py
xai_components/__init__.py
xai_components/base.py
xai_components/readme.md
xai_components/xai_controlflow/ControlflowBranch.xircuits
xai_components/xai_controlflow/ControlflowCounterLoop.xircuits
xai_components/xai_controlflow/ControlflowLoop.xircuits
xai_components/xai_controlflow/ExceptionHandlerExample.xircuits
xai_components/xai_controlflow/WorkflowComponentsExample.py
xai_components/xai_controlflow/WorkflowComponentsExample.xircuits
xai_components/xai_controlflow/__init__.py
xai_components/xai_controlflow/branches.py
xai_components/xai_controlflow/pyproject.toml
xai_components/xai_controlflow/readme.md
xai_components/xai_events/Events.xircuits
xai_components/xai_events/__init__.py
xai_components/xai_events/event_components.py
xai_components/xai_events/img.png
xai_components/xai_events/pyproject.toml
xai_components/xai_events/readme.md
xai_components/xai_template/HelloTutorial.xircuits
xai_components/xai_template/__init__.py
xai_components/xai_template/example_components.py
xai_components/xai_template/pyproject.toml
xai_components/xai_template/readme.md
xai_components/xai_template/requirements.txt
xai_components/xai_utils/RunParallelExample.xircuits
xai_components/xai_utils/UtilsZipDirectory.xircuits
xai_components/xai_utils/__init__.py
xai_components/xai_utils/pyproject.toml
xai_components/xai_utils/readme.md
xai_components/xai_utils/utils.py
xircuits/__init__.py
xircuits/_version.py
xircuits/hatch_build_hook.py
xircuits/start_xircuits.py
xircuits/utils.py
xircuits/.xircuits/.gitmodules
xircuits/.xircuits/config.ini
xircuits/compiler/__init__.py
xircuits/compiler/compiler.py
xircuits-1.19.2.dist-info/METADATA
xircuits-1.19.2.dist-info/WHEEL
xircuits-1.19.2.dist-info/entry_points.txt
xircuits-1.19.2.dist-info/licenses/LICENSE
xircuits-1.19.2.dist-info/RECORD
