Metadata-Version: 2.4
Name: xircuits
Version: 1.19.2
Dynamic: Keywords
Summary: A JupyterLab extension for rendering and editing xircuit files.
Project-URL: Homepage, https://github.com/XpressAI/xircuits
Project-URL: Bug Tracker, https://github.com/XpressAI/xircuits/issues
Project-URL: Repository, https://github.com/XpressAI/xircuits.git
Author-email: Xpress AI <eduardo@xpress.ai>
License:                                  Apache License
License-File: LICENSE
Classifier: Framework :: Jupyter
Classifier: Framework :: Jupyter :: JupyterLab
Classifier: Framework :: Jupyter :: JupyterLab :: 4
Classifier: Framework :: Jupyter :: JupyterLab :: Extensions
Classifier: Framework :: Jupyter :: JupyterLab :: Extensions :: Prebuilt
Classifier: License :: OSI Approved :: Apache Software License
Classifier: Programming Language :: Python
Classifier: Programming Language :: Python :: 3
Classifier: Programming Language :: Python :: 3.8
Classifier: Programming Language :: Python :: 3.9
Classifier: Programming Language :: Python :: 3.10
Classifier: Programming Language :: Python :: 3.11
Requires-Python: >=3.8
Requires-Dist: asgiref
Requires-Dist: dill
Requires-Dist: importlib-resources
Requires-Dist: jupyter-server<3,>=2.0.1
Requires-Dist: jupyterlab<4.5,>=4.4.0
Requires-Dist: requests
Requires-Dist: toml
Provides-Extra: test
Requires-Dist: coverage; extra == 'test'
Requires-Dist: pytest; extra == 'test'
Requires-Dist: pytest-asyncio; extra == 'test'
Requires-Dist: pytest-cov; extra == 'test'
Requires-Dist: pytest-jupyter[server]>=0.6.0; extra == 'test'
